{
  "generatedAt": "2026-06-23T03:44:25.649Z",
  "reportGeneratedAt": "2026-06-23T03:41:01.873Z",
  "status": "OK",
  "sources": {
    "yahooFinance": {
      "status": "OK",
      "lastSuccessfulFetchAt": "2026-06-23T03:40:51.000Z",
      "tickerCount": 38,
      "failedCount": 0,
      "errors": []
    },
    "fred": {
      "status": "OK",
      "lastSuccessfulFetchAt": "2026-06-22T00:00:00.000Z",
      "seriesCount": 7,
      "cachedFallbackCount": 0,
      "failedCount": 0,
      "errors": []
    }
  },
  "failedSources": []
}