{
  "artifact": "discovery-state",
  "version": 1,
  "generatedAt": "2026-07-11T02:48:04.572Z",
  "framework_version": null,
  "doctrine": "Market-wide screen before curation.",
  "snapshots": {
    "track_a": {
      "fetched_at": "2026-07-08T21:15:00-04:00",
      "total_matches": 183,
      "status": "AGING",
      "scan_id": "14576ebd-d5ac-45ac-81e1-058019206694"
    },
    "track_b": {
      "fetched_at": "2026-07-08T21:16:00-04:00",
      "total_matches": 211,
      "status": "AGING",
      "scan_id": "c0f3efdd-dfe3-4364-b983-57568193357b"
    }
  },
  "refresh_instruction": "Refresh via Robinhood MCP: run_scan on each scan_id, save results to data/discovery/scan-track-{a,b}.json with fetched_at.",
  "excluded_already_tracked": 63,
  "track_a_candidates": [
    {
      "ticker": "OR",
      "name": "OR Royalties",
      "track": "A_dislocated_quality",
      "last": 29.03,
      "rsi": 30.9,
      "gross_margin_pct": 84.8,
      "operating_margin_pct": 75,
      "market_cap_b": 5.6,
      "framework_fit": 75.1,
      "why": "RSI 30.9 with 84.8% GM / 75% OM — quality marked down, business intact pending XBRL check",
      "next_gate": "Verify revenue not declining (XBRL) + one evidence signal (insider/backlog/re-accel), then promote to scanner-universe with moat research"
    },
    {
      "ticker": "ORCL",
      "name": "Oracle",
      "track": "A_dislocated_quality",
      "last": 141.82,
      "rsi": 28.7,
      "gross_margin_pct": 65.8,
      "operating_margin_pct": 33.3,
      "market_cap_b": 407.9,
      "framework_fit": 70.8,
      "why": "RSI 28.7 with 65.8% GM / 33.3% OM — quality marked down, business intact pending XBRL check",
      "next_gate": "Verify revenue not declining (XBRL) + one evidence signal (insider/backlog/re-accel), then promote to scanner-universe with moat research"
    },
    {
      "ticker": "GLPI",
      "name": "Gaming & Leisure Properties",
      "track": "A_dislocated_quality",
      "last": 42.9,
      "rsi": 34.5,
      "gross_margin_pct": 96.6,
      "operating_margin_pct": 79.2,
      "market_cap_b": 12.5,
      "framework_fit": 69.7,
      "why": "RSI 34.5 with 96.6% GM / 79.2% OM — quality marked down, business intact pending XBRL check",
      "next_gate": "Verify revenue not declining (XBRL) + one evidence signal (insider/backlog/re-accel), then promote to scanner-universe with moat research"
    },
    {
      "ticker": "HAS",
      "name": "Hasbro",
      "track": "A_dislocated_quality",
      "last": 76.15,
      "rsi": 25.3,
      "gross_margin_pct": 64.3,
      "operating_margin_pct": 23.5,
      "market_cap_b": 10.9,
      "framework_fit": 69.4,
      "why": "RSI 25.3 with 64.3% GM / 23.5% OM — quality marked down, business intact pending XBRL check",
      "next_gate": "Verify revenue not declining (XBRL) + one evidence signal (insider/backlog/re-accel), then promote to scanner-universe with moat research"
    },
    {
      "ticker": "AEM",
      "name": "Agnico Eagle Mines",
      "track": "A_dislocated_quality",
      "last": 145.38,
      "rsi": 32,
      "gross_margin_pct": 61.8,
      "operating_margin_pct": 57.1,
      "market_cap_b": 75.1,
      "framework_fit": 68.2,
      "why": "RSI 32 with 61.8% GM / 57.1% OM — quality marked down, business intact pending XBRL check",
      "next_gate": "Verify revenue not declining (XBRL) + one evidence signal (insider/backlog/re-accel), then promote to scanner-universe with moat research"
    },
    {
      "ticker": "MPT",
      "name": "Medical Properties Trust",
      "track": "A_dislocated_quality",
      "last": 4.489,
      "rsi": 35.9,
      "gross_margin_pct": 96.1,
      "operating_margin_pct": 57,
      "market_cap_b": 2.7,
      "framework_fit": 67.7,
      "why": "RSI 35.9 with 96.1% GM / 57% OM — quality marked down, business intact pending XBRL check",
      "next_gate": "Verify revenue not declining (XBRL) + one evidence signal (insider/backlog/re-accel), then promote to scanner-universe with moat research"
    },
    {
      "ticker": "CCI",
      "name": "Crown Castle",
      "track": "A_dislocated_quality",
      "last": 76.8,
      "rsi": 36.1,
      "gross_margin_pct": 73.8,
      "operating_margin_pct": 48.5,
      "market_cap_b": 33.7,
      "framework_fit": 66.9,
      "why": "RSI 36.1 with 73.8% GM / 48.5% OM — quality marked down, business intact pending XBRL check",
      "next_gate": "Verify revenue not declining (XBRL) + one evidence signal (insider/backlog/re-accel), then promote to scanner-universe with moat research"
    },
    {
      "ticker": "AGI",
      "name": "Alamos Gold",
      "track": "A_dislocated_quality",
      "last": 29.12,
      "rsi": 32.9,
      "gross_margin_pct": 60.4,
      "operating_margin_pct": 54.5,
      "market_cap_b": 12.8,
      "framework_fit": 66.3,
      "why": "RSI 32.9 with 60.4% GM / 54.5% OM — quality marked down, business intact pending XBRL check",
      "next_gate": "Verify revenue not declining (XBRL) + one evidence signal (insider/backlog/re-accel), then promote to scanner-universe with moat research"
    },
    {
      "ticker": "WPM",
      "name": "Wheaton Precious Metals",
      "track": "A_dislocated_quality",
      "last": 108,
      "rsi": 36.8,
      "gross_margin_pct": 74.7,
      "operating_margin_pct": 71.6,
      "market_cap_b": 50.8,
      "framework_fit": 66.2,
      "why": "RSI 36.8 with 74.7% GM / 71.6% OM — quality marked down, business intact pending XBRL check",
      "next_gate": "Verify revenue not declining (XBRL) + one evidence signal (insider/backlog/re-accel), then promote to scanner-universe with moat research"
    },
    {
      "ticker": "AMT",
      "name": "American Tower",
      "track": "A_dislocated_quality",
      "last": 166.34,
      "rsi": 37.8,
      "gross_margin_pct": 74,
      "operating_margin_pct": 45.4,
      "market_cap_b": 77,
      "framework_fit": 64.4,
      "why": "RSI 37.8 with 74% GM / 45.4% OM — quality marked down, business intact pending XBRL check",
      "next_gate": "Verify revenue not declining (XBRL) + one evidence signal (insider/backlog/re-accel), then promote to scanner-universe with moat research"
    },
    {
      "ticker": "SVM",
      "name": "Silvercorp Metals",
      "track": "A_dislocated_quality",
      "last": 9.22,
      "rsi": 34.1,
      "gross_margin_pct": 57.9,
      "operating_margin_pct": 51.9,
      "market_cap_b": 2.1,
      "framework_fit": 63.5,
      "why": "RSI 34.1 with 57.9% GM / 51.9% OM — quality marked down, business intact pending XBRL check",
      "next_gate": "Verify revenue not declining (XBRL) + one evidence signal (insider/backlog/re-accel), then promote to scanner-universe with moat research"
    },
    {
      "ticker": "FNV",
      "name": "Franco-Nevada",
      "track": "A_dislocated_quality",
      "last": 201.94,
      "rsi": 39.3,
      "gross_margin_pct": 76.6,
      "operating_margin_pct": 74.4,
      "market_cap_b": 40.4,
      "framework_fit": 62.5,
      "why": "RSI 39.3 with 76.6% GM / 74.4% OM — quality marked down, business intact pending XBRL check",
      "next_gate": "Verify revenue not declining (XBRL) + one evidence signal (insider/backlog/re-accel), then promote to scanner-universe with moat research"
    }
  ],
  "track_b_candidates": [
    {
      "ticker": "IOT",
      "name": "Samsara",
      "track": "B_inflection_leaders",
      "last": 36.69,
      "rsi": 62,
      "gross_margin_pct": 76.7,
      "operating_margin_pct": 0,
      "market_cap_b": 21.2,
      "framework_fit": 45,
      "why": "RSI 62 holding strength with 76.7% GM and positive EPS — inflection candidate pending event check",
      "next_gate": "Verify dated inflection event within 2 quarters + not >25% above 20d base, then promote"
    },
    {
      "ticker": "INDV",
      "name": "Indivior Pharmaceuticals",
      "track": "B_inflection_leaders",
      "last": 40.89,
      "rsi": 62.1,
      "gross_margin_pct": 81.2,
      "operating_margin_pct": 0,
      "market_cap_b": 4.8,
      "framework_fit": 44.9,
      "why": "RSI 62.1 holding strength with 81.2% GM and positive EPS — inflection candidate pending event check",
      "next_gate": "Verify dated inflection event within 2 quarters + not >25% above 20d base, then promote"
    },
    {
      "ticker": "NVO",
      "name": "Novo Nordisk",
      "track": "B_inflection_leaders",
      "last": 48.895,
      "rsi": 62.2,
      "gross_margin_pct": 81.8,
      "operating_margin_pct": 0,
      "market_cap_b": 220.2,
      "framework_fit": 44.8,
      "why": "RSI 62.2 holding strength with 81.8% GM and positive EPS — inflection candidate pending event check",
      "next_gate": "Verify dated inflection event within 2 quarters + not >25% above 20d base, then promote"
    },
    {
      "ticker": "BMRN",
      "name": "BioMarin",
      "track": "B_inflection_leaders",
      "last": 59.74,
      "rsi": 62.4,
      "gross_margin_pct": 76.5,
      "operating_margin_pct": 0,
      "market_cap_b": 11.7,
      "framework_fit": 44.6,
      "why": "RSI 62.4 holding strength with 76.5% GM and positive EPS — inflection candidate pending event check",
      "next_gate": "Verify dated inflection event within 2 quarters + not >25% above 20d base, then promote"
    },
    {
      "ticker": "DBX",
      "name": "Dropbox",
      "track": "B_inflection_leaders",
      "last": 28.85,
      "rsi": 62.4,
      "gross_margin_pct": 79.7,
      "operating_margin_pct": 0,
      "market_cap_b": 6.7,
      "framework_fit": 44.6,
      "why": "RSI 62.4 holding strength with 79.7% GM and positive EPS — inflection candidate pending event check",
      "next_gate": "Verify dated inflection event within 2 quarters + not >25% above 20d base, then promote"
    },
    {
      "ticker": "CARG",
      "name": "CarGurus",
      "track": "B_inflection_leaders",
      "last": 33.75,
      "rsi": 61.5,
      "gross_margin_pct": 92.5,
      "operating_margin_pct": 0,
      "market_cap_b": 3.2,
      "framework_fit": 44.5,
      "why": "RSI 61.5 holding strength with 92.5% GM and positive EPS — inflection candidate pending event check",
      "next_gate": "Verify dated inflection event within 2 quarters + not >25% above 20d base, then promote"
    },
    {
      "ticker": "CCC",
      "name": "CCC Intelligent Solutions",
      "track": "B_inflection_leaders",
      "last": 5.4185,
      "rsi": 61.9,
      "gross_margin_pct": 73.7,
      "operating_margin_pct": 0,
      "market_cap_b": 3.3,
      "framework_fit": 44.4,
      "why": "RSI 61.9 holding strength with 73.7% GM and positive EPS — inflection candidate pending event check",
      "next_gate": "Verify dated inflection event within 2 quarters + not >25% above 20d base, then promote"
    },
    {
      "ticker": "PINS",
      "name": "Pinterest",
      "track": "B_inflection_leaders",
      "last": 22.61,
      "rsi": 61.3,
      "gross_margin_pct": 79.9,
      "operating_margin_pct": 0,
      "market_cap_b": 12.6,
      "framework_fit": 44.3,
      "why": "RSI 61.3 holding strength with 79.9% GM and positive EPS — inflection candidate pending event check",
      "next_gate": "Verify dated inflection event within 2 quarters + not >25% above 20d base, then promote"
    },
    {
      "ticker": "FTNT",
      "name": "Fortinet",
      "track": "B_inflection_leaders",
      "last": 156.85,
      "rsi": 62.8,
      "gross_margin_pct": 80.3,
      "operating_margin_pct": 0,
      "market_cap_b": 116.2,
      "framework_fit": 44.2,
      "why": "RSI 62.8 holding strength with 80.3% GM and positive EPS — inflection candidate pending event check",
      "next_gate": "Verify dated inflection event within 2 quarters + not >25% above 20d base, then promote"
    },
    {
      "ticker": "CHKP",
      "name": "Check Point Software Technologies",
      "track": "B_inflection_leaders",
      "last": 136.85,
      "rsi": 61.2,
      "gross_margin_pct": 86.4,
      "operating_margin_pct": 0,
      "market_cap_b": 14.4,
      "framework_fit": 44.2,
      "why": "RSI 61.2 holding strength with 86.4% GM and positive EPS — inflection candidate pending event check",
      "next_gate": "Verify dated inflection event within 2 quarters + not >25% above 20d base, then promote"
    },
    {
      "ticker": "MCO",
      "name": "Moody's",
      "track": "B_inflection_leaders",
      "last": 485.1,
      "rsi": 61.2,
      "gross_margin_pct": 74.4,
      "operating_margin_pct": 0,
      "market_cap_b": 87.4,
      "framework_fit": 44,
      "why": "RSI 61.2 holding strength with 74.4% GM and positive EPS — inflection candidate pending event check",
      "next_gate": "Verify dated inflection event within 2 quarters + not >25% above 20d base, then promote"
    },
    {
      "ticker": "EA",
      "name": "EA",
      "track": "B_inflection_leaders",
      "last": 204.23,
      "rsi": 61,
      "gross_margin_pct": 79,
      "operating_margin_pct": 0,
      "market_cap_b": 51.5,
      "framework_fit": 44,
      "why": "RSI 61 holding strength with 79% GM and positive EPS — inflection candidate pending event check",
      "next_gate": "Verify dated inflection event within 2 quarters + not >25% above 20d base, then promote"
    }
  ],
  "full_counts": {
    "track_a_new": 175,
    "track_b_new": 194
  }
}
