{
  "generatedAt": "2026-06-26T19:18:10.426Z",
  "reviewQueue": [
    {
      "ticker": "CONL",
      "signal": "EXIT REVIEW",
      "authority": {
        "state": "exit_review",
        "label": "Exit review",
        "scoreCap": 44,
        "uiClass": "bad",
        "reason": "Authoritative signal is EXIT REVIEW; support labels are suppressed."
      },
      "composite": 44,
      "weakest": {
        "name": "Price trend",
        "score": 0,
        "status": "weak",
        "finding": "Day +5.63%, 5D -20.09%, 1M -32.47%, 3M -43.67%."
      },
      "strongest": {
        "name": "Portfolio concentration",
        "score": 98,
        "status": "supportive",
        "finding": "0.31% versus 5% speculative/levered budget."
      },
      "factors": [
        {
          "name": "Price trend",
          "score": 0,
          "status": "weak",
          "finding": "Day +5.63%, 5D -20.09%, 1M -32.47%, 3M -43.67%."
        },
        {
          "name": "Valuation",
          "score": 35,
          "status": "weak",
          "finding": "Forward PE and FCF yield missing."
        },
        {
          "name": "Portfolio concentration",
          "score": 98,
          "status": "supportive",
          "finding": "0.31% versus 5% speculative/levered budget."
        },
        {
          "name": "Earnings / event risk",
          "score": 45,
          "status": "mixed",
          "finding": "Earnings date N/A; timing unclear."
        },
        {
          "name": "Liquidity / flow",
          "score": 45,
          "status": "mixed",
          "finding": "Volume data missing."
        },
        {
          "name": "Macro sensitivity",
          "score": 34,
          "status": "weak",
          "finding": "Risk appetite: mixed / risk watch · Crypto liquidity beta: contracting · Credit conditions: benign / watch"
        },
        {
          "name": "Thesis confidence",
          "score": 68,
          "status": "mixed",
          "finding": "Thesis/rationale exists; check invalidation specificity."
        },
        {
          "name": "Data completeness",
          "score": 43,
          "status": "weak",
          "finding": "1/3 contract fields complete; price available."
        }
      ]
    },
    {
      "ticker": "SPY",
      "signal": "HOLD",
      "authority": {
        "state": "normal",
        "label": null,
        "scoreCap": 100,
        "uiClass": null,
        "reason": null
      },
      "composite": 46,
      "weakest": {
        "name": "Portfolio concentration",
        "score": 0,
        "status": "weak",
        "finding": "56.64% versus 15% single non-index budget."
      },
      "strongest": {
        "name": "Data completeness",
        "score": 90,
        "status": "supportive",
        "finding": "3/3 contract fields complete; price available."
      },
      "factors": [
        {
          "name": "Price trend",
          "score": 57,
          "status": "mixed",
          "finding": "Day -0.26%, 5D -1.93%, 1M -2.41%, 3M +12.12%."
        },
        {
          "name": "Valuation",
          "score": 66,
          "status": "mixed",
          "finding": "Forward PE 22.10; FCF yield 3.30%."
        },
        {
          "name": "Portfolio concentration",
          "score": 0,
          "status": "weak",
          "finding": "56.64% versus 15% single non-index budget."
        },
        {
          "name": "Earnings / event risk",
          "score": 45,
          "status": "mixed",
          "finding": "Earnings date N/A; timing unclear."
        },
        {
          "name": "Liquidity / flow",
          "score": 45,
          "status": "mixed",
          "finding": "Volume data missing."
        },
        {
          "name": "Macro sensitivity",
          "score": 4,
          "status": "weak",
          "finding": "Rates pressure: rising / restrictive · Risk appetite: mixed / risk watch · Credit conditions: benign / watch · Inflation expectation: contained watch"
        },
        {
          "name": "Thesis confidence",
          "score": 60,
          "status": "mixed",
          "finding": "Thesis/rationale exists; check invalidation specificity."
        },
        {
          "name": "Data completeness",
          "score": 90,
          "status": "supportive",
          "finding": "3/3 contract fields complete; price available."
        }
      ]
    },
    {
      "ticker": "BMNR",
      "signal": "INVESTIGATE",
      "authority": {
        "state": "investigate",
        "label": "Investigate",
        "scoreCap": 54,
        "uiClass": "warn",
        "reason": "Authoritative signal is INVESTIGATE; support labels are suppressed until verified."
      },
      "composite": 46,
      "weakest": {
        "name": "Price trend",
        "score": 0,
        "status": "weak",
        "finding": "Day +1.88%, 5D -15.92%, 1M -27.90%, 3M -34.76%."
      },
      "strongest": {
        "name": "Earnings / event risk",
        "score": 75,
        "status": "supportive",
        "finding": "Next earnings in 33 trading days."
      },
      "factors": [
        {
          "name": "Price trend",
          "score": 0,
          "status": "weak",
          "finding": "Day +1.88%, 5D -15.92%, 1M -27.90%, 3M -34.76%."
        },
        {
          "name": "Valuation",
          "score": 38,
          "status": "weak",
          "finding": "Forward PE missing; FCF yield -8.50%."
        },
        {
          "name": "Portfolio concentration",
          "score": 20,
          "status": "weak",
          "finding": "8.25% versus 5% speculative/levered budget."
        },
        {
          "name": "Earnings / event risk",
          "score": 75,
          "status": "supportive",
          "finding": "Next earnings in 33 trading days."
        },
        {
          "name": "Liquidity / flow",
          "score": 45,
          "status": "mixed",
          "finding": "Volume data missing."
        },
        {
          "name": "Macro sensitivity",
          "score": 55,
          "status": "mixed",
          "finding": "No explicit macro force mapped."
        },
        {
          "name": "Thesis confidence",
          "score": 68,
          "status": "mixed",
          "finding": "Thesis/rationale exists; check invalidation specificity."
        },
        {
          "name": "Data completeness",
          "score": 67,
          "status": "mixed",
          "finding": "2/3 contract fields complete; price available."
        }
      ]
    },
    {
      "ticker": "TSLT",
      "signal": "TRIM WATCH",
      "authority": {
        "state": "trim_watch",
        "label": "Trim watch",
        "scoreCap": 49,
        "uiClass": "bad",
        "reason": "Authoritative signal is TRIM WATCH; support labels are suppressed."
      },
      "composite": 47,
      "weakest": {
        "name": "Price trend",
        "score": 15,
        "status": "weak",
        "finding": "Day +2.57%, 5D -10.36%, 1M -27.91%, 3M -10.07%."
      },
      "strongest": {
        "name": "Portfolio concentration",
        "score": 98,
        "status": "supportive",
        "finding": "0.44% versus 5% speculative/levered budget."
      },
      "factors": [
        {
          "name": "Price trend",
          "score": 15,
          "status": "weak",
          "finding": "Day +2.57%, 5D -10.36%, 1M -27.91%, 3M -10.07%."
        },
        {
          "name": "Valuation",
          "score": 35,
          "status": "weak",
          "finding": "Forward PE and FCF yield missing."
        },
        {
          "name": "Portfolio concentration",
          "score": 98,
          "status": "supportive",
          "finding": "0.44% versus 5% speculative/levered budget."
        },
        {
          "name": "Earnings / event risk",
          "score": 45,
          "status": "mixed",
          "finding": "Earnings date N/A; timing unclear."
        },
        {
          "name": "Liquidity / flow",
          "score": 45,
          "status": "mixed",
          "finding": "Volume data missing."
        },
        {
          "name": "Macro sensitivity",
          "score": 27,
          "status": "weak",
          "finding": "Risk appetite: mixed / risk watch · Credit conditions: benign / watch"
        },
        {
          "name": "Thesis confidence",
          "score": 68,
          "status": "mixed",
          "finding": "Thesis/rationale exists; check invalidation specificity."
        },
        {
          "name": "Data completeness",
          "score": 43,
          "status": "weak",
          "finding": "1/3 contract fields complete; price available."
        }
      ]
    },
    {
      "ticker": "AMZN",
      "signal": "HOLD / WATCH",
      "authority": {
        "state": "normal",
        "label": null,
        "scoreCap": 100,
        "uiClass": null,
        "reason": null
      },
      "composite": 50,
      "weakest": {
        "name": "Portfolio concentration",
        "score": 0,
        "status": "weak",
        "finding": "13.61% versus 5% speculative/levered budget."
      },
      "strongest": {
        "name": "Data completeness",
        "score": 90,
        "status": "supportive",
        "finding": "3/3 contract fields complete; price available."
      },
      "factors": [
        {
          "name": "Price trend",
          "score": 42,
          "status": "weak",
          "finding": "Day +0.63%, 5D -6.53%, 1M -15.97%, 3M +10.23%."
        },
        {
          "name": "Valuation",
          "score": 53,
          "status": "mixed",
          "finding": "Forward PE 34.80; FCF yield 2.10%."
        },
        {
          "name": "Portfolio concentration",
          "score": 0,
          "status": "weak",
          "finding": "13.61% versus 5% speculative/levered budget."
        },
        {
          "name": "Earnings / event risk",
          "score": 75,
          "status": "supportive",
          "finding": "Next earnings in 24 trading days."
        },
        {
          "name": "Liquidity / flow",
          "score": 45,
          "status": "mixed",
          "finding": "Volume data missing."
        },
        {
          "name": "Macro sensitivity",
          "score": 34,
          "status": "weak",
          "finding": "Rates pressure: rising / restrictive · AI infrastructure: cooling · Inflation expectation: contained watch"
        },
        {
          "name": "Thesis confidence",
          "score": 60,
          "status": "mixed",
          "finding": "Thesis/rationale exists; check invalidation specificity."
        },
        {
          "name": "Data completeness",
          "score": 90,
          "status": "supportive",
          "finding": "3/3 contract fields complete; price available."
        }
      ]
    }
  ],
  "strongest": [
    {
      "ticker": "MA",
      "signal": "HOLD",
      "authority": {
        "state": "normal",
        "label": null,
        "scoreCap": 100,
        "uiClass": null,
        "reason": null
      },
      "composite": 66,
      "weakest": {
        "name": "Macro sensitivity",
        "score": 41,
        "status": "weak",
        "finding": "Inflation expectation: contained watch"
      },
      "strongest": {
        "name": "Portfolio concentration",
        "score": 94,
        "status": "supportive",
        "finding": "3.59% versus 15% single non-index budget."
      },
      "factors": [
        {
          "name": "Price trend",
          "score": 53,
          "status": "mixed",
          "finding": "Day +2.25%, 5D +2.07%, 1M +0.99%, 3M +0.20%."
        },
        {
          "name": "Valuation",
          "score": 66,
          "status": "mixed",
          "finding": "Forward PE 28.90; FCF yield 2.60%."
        },
        {
          "name": "Portfolio concentration",
          "score": 94,
          "status": "supportive",
          "finding": "3.59% versus 15% single non-index budget."
        },
        {
          "name": "Earnings / event risk",
          "score": 75,
          "status": "supportive",
          "finding": "Next earnings in 24 trading days."
        },
        {
          "name": "Liquidity / flow",
          "score": 45,
          "status": "mixed",
          "finding": "Volume data missing."
        },
        {
          "name": "Macro sensitivity",
          "score": 41,
          "status": "weak",
          "finding": "Inflation expectation: contained watch"
        },
        {
          "name": "Thesis confidence",
          "score": 60,
          "status": "mixed",
          "finding": "Thesis/rationale exists; check invalidation specificity."
        },
        {
          "name": "Data completeness",
          "score": 90,
          "status": "supportive",
          "finding": "3/3 contract fields complete; price available."
        }
      ]
    },
    {
      "ticker": "MSFT",
      "signal": "HOLD",
      "authority": {
        "state": "normal",
        "label": null,
        "scoreCap": 100,
        "uiClass": null,
        "reason": null
      },
      "composite": 65,
      "weakest": {
        "name": "Price trend",
        "score": 42,
        "status": "weak",
        "finding": "Day +5.13%, 5D -2.23%, 1M -10.11%, 3M -0.48%."
      },
      "strongest": {
        "name": "Portfolio concentration",
        "score": 97,
        "status": "supportive",
        "finding": "1.99% versus 15% single non-index budget."
      },
      "factors": [
        {
          "name": "Price trend",
          "score": 42,
          "status": "weak",
          "finding": "Day +5.13%, 5D -2.23%, 1M -10.11%, 3M -0.48%."
        },
        {
          "name": "Valuation",
          "score": 66,
          "status": "mixed",
          "finding": "Forward PE 28.40; FCF yield 2.70%."
        },
        {
          "name": "Portfolio concentration",
          "score": 97,
          "status": "supportive",
          "finding": "1.99% versus 15% single non-index budget."
        },
        {
          "name": "Earnings / event risk",
          "score": 75,
          "status": "supportive",
          "finding": "Next earnings in 22 trading days."
        },
        {
          "name": "Liquidity / flow",
          "score": 45,
          "status": "mixed",
          "finding": "Volume data missing."
        },
        {
          "name": "Macro sensitivity",
          "score": 47,
          "status": "mixed",
          "finding": "Rates pressure: rising / restrictive · AI infrastructure: cooling"
        },
        {
          "name": "Thesis confidence",
          "score": 60,
          "status": "mixed",
          "finding": "Thesis/rationale exists; check invalidation specificity."
        },
        {
          "name": "Data completeness",
          "score": 90,
          "status": "supportive",
          "finding": "3/3 contract fields complete; price available."
        }
      ]
    },
    {
      "ticker": "CEG",
      "signal": "HOLD / WATCH",
      "authority": {
        "state": "normal",
        "label": null,
        "scoreCap": 100,
        "uiClass": null,
        "reason": null
      },
      "composite": 63,
      "weakest": {
        "name": "Price trend",
        "score": 30,
        "status": "weak",
        "finding": "Day -2.78%, 5D -4.68%, 1M -9.51%, 3M -11.40%."
      },
      "strongest": {
        "name": "Portfolio concentration",
        "score": 98,
        "status": "supportive",
        "finding": "1.40% versus 15% single non-index budget."
      },
      "factors": [
        {
          "name": "Price trend",
          "score": 30,
          "status": "weak",
          "finding": "Day -2.78%, 5D -4.68%, 1M -9.51%, 3M -11.40%."
        },
        {
          "name": "Valuation",
          "score": 54,
          "status": "mixed",
          "finding": "Forward PE 27.60; FCF yield 1.40%."
        },
        {
          "name": "Portfolio concentration",
          "score": 98,
          "status": "supportive",
          "finding": "1.40% versus 15% single non-index budget."
        },
        {
          "name": "Earnings / event risk",
          "score": 75,
          "status": "supportive",
          "finding": "Next earnings in 29 trading days."
        },
        {
          "name": "Liquidity / flow",
          "score": 45,
          "status": "mixed",
          "finding": "Volume data missing."
        },
        {
          "name": "Macro sensitivity",
          "score": 47,
          "status": "mixed",
          "finding": "Rates pressure: rising / restrictive · AI infrastructure: cooling"
        },
        {
          "name": "Thesis confidence",
          "score": 68,
          "status": "mixed",
          "finding": "Thesis/rationale exists; check invalidation specificity."
        },
        {
          "name": "Data completeness",
          "score": 90,
          "status": "supportive",
          "finding": "3/3 contract fields complete; price available."
        }
      ]
    }
  ],
  "warnings": [
    {
      "ticker": "AMZN",
      "signal": "HOLD / WATCH",
      "factor": "Portfolio concentration",
      "score": 0,
      "finding": "13.61% versus 5% speculative/levered budget."
    },
    {
      "ticker": "CONL",
      "signal": "EXIT REVIEW",
      "factor": "Price trend",
      "score": 0,
      "finding": "Day +5.63%, 5D -20.09%, 1M -32.47%, 3M -43.67%."
    },
    {
      "ticker": "SPY",
      "signal": "HOLD",
      "factor": "Portfolio concentration",
      "score": 0,
      "finding": "56.64% versus 15% single non-index budget."
    },
    {
      "ticker": "BMNR",
      "signal": "INVESTIGATE",
      "factor": "Price trend",
      "score": 0,
      "finding": "Day +1.88%, 5D -15.92%, 1M -27.90%, 3M -34.76%."
    },
    {
      "ticker": "SPY",
      "signal": "HOLD",
      "factor": "Macro sensitivity",
      "score": 4,
      "finding": "Rates pressure: rising / restrictive · Risk appetite: mixed / risk watch · Credit conditions: benign / watch · Inflation expectation: contained watch"
    },
    {
      "ticker": "TSLT",
      "signal": "TRIM WATCH",
      "factor": "Price trend",
      "score": 15,
      "finding": "Day +2.57%, 5D -10.36%, 1M -27.91%, 3M -10.07%."
    },
    {
      "ticker": "BMNR",
      "signal": "INVESTIGATE",
      "factor": "Portfolio concentration",
      "score": 20,
      "finding": "8.25% versus 5% speculative/levered budget."
    },
    {
      "ticker": "META",
      "signal": "HOLD / WATCH",
      "factor": "Portfolio concentration",
      "score": 21,
      "finding": "8.20% versus 5% speculative/levered budget."
    },
    {
      "ticker": "NFLX",
      "signal": "HOLD / WATCH",
      "factor": "Price trend",
      "score": 22,
      "finding": "Day +4.10%, 5D -4.62%, 1M -15.51%, 3M -18.82%."
    },
    {
      "ticker": "TSLT",
      "signal": "TRIM WATCH",
      "factor": "Macro sensitivity",
      "score": 27,
      "finding": "Risk appetite: mixed / risk watch · Credit conditions: benign / watch"
    },
    {
      "ticker": "NFLX",
      "signal": "HOLD / WATCH",
      "factor": "Macro sensitivity",
      "score": 29,
      "finding": "Rates pressure: rising / restrictive · Inflation expectation: contained watch"
    },
    {
      "ticker": "CEG",
      "signal": "HOLD / WATCH",
      "factor": "Price trend",
      "score": 30,
      "finding": "Day -2.78%, 5D -4.68%, 1M -9.51%, 3M -11.40%."
    },
    {
      "ticker": "META",
      "signal": "HOLD / WATCH",
      "factor": "Price trend",
      "score": 32,
      "finding": "Day +1.36%, 5D -4.67%, 1M -13.38%, 3M -7.19%."
    },
    {
      "ticker": "AMZN",
      "signal": "HOLD / WATCH",
      "factor": "Macro sensitivity",
      "score": 34,
      "finding": "Rates pressure: rising / restrictive · AI infrastructure: cooling · Inflation expectation: contained watch"
    },
    {
      "ticker": "CONL",
      "signal": "EXIT REVIEW",
      "factor": "Macro sensitivity",
      "score": 34,
      "finding": "Risk appetite: mixed / risk watch · Crypto liquidity beta: contracting · Credit conditions: benign / watch"
    },
    {
      "ticker": "TSLT",
      "signal": "TRIM WATCH",
      "factor": "Valuation",
      "score": 35,
      "finding": "Forward PE and FCF yield missing."
    },
    {
      "ticker": "CONL",
      "signal": "EXIT REVIEW",
      "factor": "Valuation",
      "score": 35,
      "finding": "Forward PE and FCF yield missing."
    },
    {
      "ticker": "BMNR",
      "signal": "INVESTIGATE",
      "factor": "Valuation",
      "score": 38,
      "finding": "Forward PE missing; FCF yield -8.50%."
    },
    {
      "ticker": "MA",
      "signal": "HOLD",
      "factor": "Macro sensitivity",
      "score": 41,
      "finding": "Inflation expectation: contained watch"
    },
    {
      "ticker": "MSFT",
      "signal": "HOLD",
      "factor": "Price trend",
      "score": 42,
      "finding": "Day +5.13%, 5D -2.23%, 1M -10.11%, 3M -0.48%."
    },
    {
      "ticker": "AMZN",
      "signal": "HOLD / WATCH",
      "factor": "Price trend",
      "score": 42,
      "finding": "Day +0.63%, 5D -6.53%, 1M -15.97%, 3M +10.23%."
    },
    {
      "ticker": "TSLT",
      "signal": "TRIM WATCH",
      "factor": "Data completeness",
      "score": 43,
      "finding": "1/3 contract fields complete; price available."
    },
    {
      "ticker": "CONL",
      "signal": "EXIT REVIEW",
      "factor": "Data completeness",
      "score": 43,
      "finding": "1/3 contract fields complete; price available."
    }
  ],
  "dataGaps": [
    {
      "ticker": "TSLT",
      "signal": "TRIM WATCH",
      "factor": "Valuation",
      "score": 35,
      "finding": "Forward PE and FCF yield missing."
    },
    {
      "ticker": "CONL",
      "signal": "EXIT REVIEW",
      "factor": "Valuation",
      "score": 35,
      "finding": "Forward PE and FCF yield missing."
    },
    {
      "ticker": "BMNR",
      "signal": "INVESTIGATE",
      "factor": "Valuation",
      "score": 38,
      "finding": "Forward PE missing; FCF yield -8.50%."
    },
    {
      "ticker": "TSLT",
      "signal": "TRIM WATCH",
      "factor": "Data completeness",
      "score": 43,
      "finding": "1/3 contract fields complete; price available."
    },
    {
      "ticker": "CONL",
      "signal": "EXIT REVIEW",
      "factor": "Data completeness",
      "score": 43,
      "finding": "1/3 contract fields complete; price available."
    }
  ],
  "concentration": [
    {
      "ticker": "AMZN",
      "signal": "HOLD / WATCH",
      "factor": "Portfolio concentration",
      "score": 0,
      "finding": "13.61% versus 5% speculative/levered budget."
    },
    {
      "ticker": "SPY",
      "signal": "HOLD",
      "factor": "Portfolio concentration",
      "score": 0,
      "finding": "56.64% versus 15% single non-index budget."
    },
    {
      "ticker": "BMNR",
      "signal": "INVESTIGATE",
      "factor": "Portfolio concentration",
      "score": 20,
      "finding": "8.25% versus 5% speculative/levered budget."
    },
    {
      "ticker": "META",
      "signal": "HOLD / WATCH",
      "factor": "Portfolio concentration",
      "score": 21,
      "finding": "8.20% versus 5% speculative/levered budget."
    }
  ],
  "scorecards": [
    {
      "ticker": "MSFT",
      "signal": "HOLD",
      "authority": {
        "state": "normal",
        "label": null,
        "scoreCap": 100,
        "uiClass": null,
        "reason": null
      },
      "composite": 65,
      "weakest": {
        "name": "Price trend",
        "score": 42,
        "status": "weak",
        "finding": "Day +5.13%, 5D -2.23%, 1M -10.11%, 3M -0.48%."
      },
      "strongest": {
        "name": "Portfolio concentration",
        "score": 97,
        "status": "supportive",
        "finding": "1.99% versus 15% single non-index budget."
      },
      "factors": [
        {
          "name": "Price trend",
          "score": 42,
          "status": "weak",
          "finding": "Day +5.13%, 5D -2.23%, 1M -10.11%, 3M -0.48%."
        },
        {
          "name": "Valuation",
          "score": 66,
          "status": "mixed",
          "finding": "Forward PE 28.40; FCF yield 2.70%."
        },
        {
          "name": "Portfolio concentration",
          "score": 97,
          "status": "supportive",
          "finding": "1.99% versus 15% single non-index budget."
        },
        {
          "name": "Earnings / event risk",
          "score": 75,
          "status": "supportive",
          "finding": "Next earnings in 22 trading days."
        },
        {
          "name": "Liquidity / flow",
          "score": 45,
          "status": "mixed",
          "finding": "Volume data missing."
        },
        {
          "name": "Macro sensitivity",
          "score": 47,
          "status": "mixed",
          "finding": "Rates pressure: rising / restrictive · AI infrastructure: cooling"
        },
        {
          "name": "Thesis confidence",
          "score": 60,
          "status": "mixed",
          "finding": "Thesis/rationale exists; check invalidation specificity."
        },
        {
          "name": "Data completeness",
          "score": 90,
          "status": "supportive",
          "finding": "3/3 contract fields complete; price available."
        }
      ]
    },
    {
      "ticker": "AMZN",
      "signal": "HOLD / WATCH",
      "authority": {
        "state": "normal",
        "label": null,
        "scoreCap": 100,
        "uiClass": null,
        "reason": null
      },
      "composite": 50,
      "weakest": {
        "name": "Portfolio concentration",
        "score": 0,
        "status": "weak",
        "finding": "13.61% versus 5% speculative/levered budget."
      },
      "strongest": {
        "name": "Data completeness",
        "score": 90,
        "status": "supportive",
        "finding": "3/3 contract fields complete; price available."
      },
      "factors": [
        {
          "name": "Price trend",
          "score": 42,
          "status": "weak",
          "finding": "Day +0.63%, 5D -6.53%, 1M -15.97%, 3M +10.23%."
        },
        {
          "name": "Valuation",
          "score": 53,
          "status": "mixed",
          "finding": "Forward PE 34.80; FCF yield 2.10%."
        },
        {
          "name": "Portfolio concentration",
          "score": 0,
          "status": "weak",
          "finding": "13.61% versus 5% speculative/levered budget."
        },
        {
          "name": "Earnings / event risk",
          "score": 75,
          "status": "supportive",
          "finding": "Next earnings in 24 trading days."
        },
        {
          "name": "Liquidity / flow",
          "score": 45,
          "status": "mixed",
          "finding": "Volume data missing."
        },
        {
          "name": "Macro sensitivity",
          "score": 34,
          "status": "weak",
          "finding": "Rates pressure: rising / restrictive · AI infrastructure: cooling · Inflation expectation: contained watch"
        },
        {
          "name": "Thesis confidence",
          "score": 60,
          "status": "mixed",
          "finding": "Thesis/rationale exists; check invalidation specificity."
        },
        {
          "name": "Data completeness",
          "score": 90,
          "status": "supportive",
          "finding": "3/3 contract fields complete; price available."
        }
      ]
    },
    {
      "ticker": "CEG",
      "signal": "HOLD / WATCH",
      "authority": {
        "state": "normal",
        "label": null,
        "scoreCap": 100,
        "uiClass": null,
        "reason": null
      },
      "composite": 63,
      "weakest": {
        "name": "Price trend",
        "score": 30,
        "status": "weak",
        "finding": "Day -2.78%, 5D -4.68%, 1M -9.51%, 3M -11.40%."
      },
      "strongest": {
        "name": "Portfolio concentration",
        "score": 98,
        "status": "supportive",
        "finding": "1.40% versus 15% single non-index budget."
      },
      "factors": [
        {
          "name": "Price trend",
          "score": 30,
          "status": "weak",
          "finding": "Day -2.78%, 5D -4.68%, 1M -9.51%, 3M -11.40%."
        },
        {
          "name": "Valuation",
          "score": 54,
          "status": "mixed",
          "finding": "Forward PE 27.60; FCF yield 1.40%."
        },
        {
          "name": "Portfolio concentration",
          "score": 98,
          "status": "supportive",
          "finding": "1.40% versus 15% single non-index budget."
        },
        {
          "name": "Earnings / event risk",
          "score": 75,
          "status": "supportive",
          "finding": "Next earnings in 29 trading days."
        },
        {
          "name": "Liquidity / flow",
          "score": 45,
          "status": "mixed",
          "finding": "Volume data missing."
        },
        {
          "name": "Macro sensitivity",
          "score": 47,
          "status": "mixed",
          "finding": "Rates pressure: rising / restrictive · AI infrastructure: cooling"
        },
        {
          "name": "Thesis confidence",
          "score": 68,
          "status": "mixed",
          "finding": "Thesis/rationale exists; check invalidation specificity."
        },
        {
          "name": "Data completeness",
          "score": 90,
          "status": "supportive",
          "finding": "3/3 contract fields complete; price available."
        }
      ]
    },
    {
      "ticker": "META",
      "signal": "HOLD / WATCH",
      "authority": {
        "state": "normal",
        "label": null,
        "scoreCap": 100,
        "uiClass": null,
        "reason": null
      },
      "composite": 55,
      "weakest": {
        "name": "Portfolio concentration",
        "score": 21,
        "status": "weak",
        "finding": "8.20% versus 5% speculative/levered budget."
      },
      "strongest": {
        "name": "Data completeness",
        "score": 90,
        "status": "supportive",
        "finding": "3/3 contract fields complete; price available."
      },
      "factors": [
        {
          "name": "Price trend",
          "score": 32,
          "status": "weak",
          "finding": "Day +1.36%, 5D -4.67%, 1M -13.38%, 3M -7.19%."
        },
        {
          "name": "Valuation",
          "score": 66,
          "status": "mixed",
          "finding": "Forward PE 21.70; FCF yield 4.10%."
        },
        {
          "name": "Portfolio concentration",
          "score": 21,
          "status": "weak",
          "finding": "8.20% versus 5% speculative/levered budget."
        },
        {
          "name": "Earnings / event risk",
          "score": 75,
          "status": "supportive",
          "finding": "Next earnings in 23 trading days."
        },
        {
          "name": "Liquidity / flow",
          "score": 45,
          "status": "mixed",
          "finding": "Volume data missing."
        },
        {
          "name": "Macro sensitivity",
          "score": 47,
          "status": "mixed",
          "finding": "Rates pressure: rising / restrictive · AI infrastructure: cooling"
        },
        {
          "name": "Thesis confidence",
          "score": 60,
          "status": "mixed",
          "finding": "Thesis/rationale exists; check invalidation specificity."
        },
        {
          "name": "Data completeness",
          "score": 90,
          "status": "supportive",
          "finding": "3/3 contract fields complete; price available."
        }
      ]
    },
    {
      "ticker": "TSLT",
      "signal": "TRIM WATCH",
      "authority": {
        "state": "trim_watch",
        "label": "Trim watch",
        "scoreCap": 49,
        "uiClass": "bad",
        "reason": "Authoritative signal is TRIM WATCH; support labels are suppressed."
      },
      "composite": 47,
      "weakest": {
        "name": "Price trend",
        "score": 15,
        "status": "weak",
        "finding": "Day +2.57%, 5D -10.36%, 1M -27.91%, 3M -10.07%."
      },
      "strongest": {
        "name": "Portfolio concentration",
        "score": 98,
        "status": "supportive",
        "finding": "0.44% versus 5% speculative/levered budget."
      },
      "factors": [
        {
          "name": "Price trend",
          "score": 15,
          "status": "weak",
          "finding": "Day +2.57%, 5D -10.36%, 1M -27.91%, 3M -10.07%."
        },
        {
          "name": "Valuation",
          "score": 35,
          "status": "weak",
          "finding": "Forward PE and FCF yield missing."
        },
        {
          "name": "Portfolio concentration",
          "score": 98,
          "status": "supportive",
          "finding": "0.44% versus 5% speculative/levered budget."
        },
        {
          "name": "Earnings / event risk",
          "score": 45,
          "status": "mixed",
          "finding": "Earnings date N/A; timing unclear."
        },
        {
          "name": "Liquidity / flow",
          "score": 45,
          "status": "mixed",
          "finding": "Volume data missing."
        },
        {
          "name": "Macro sensitivity",
          "score": 27,
          "status": "weak",
          "finding": "Risk appetite: mixed / risk watch · Credit conditions: benign / watch"
        },
        {
          "name": "Thesis confidence",
          "score": 68,
          "status": "mixed",
          "finding": "Thesis/rationale exists; check invalidation specificity."
        },
        {
          "name": "Data completeness",
          "score": 43,
          "status": "weak",
          "finding": "1/3 contract fields complete; price available."
        }
      ]
    },
    {
      "ticker": "CONL",
      "signal": "EXIT REVIEW",
      "authority": {
        "state": "exit_review",
        "label": "Exit review",
        "scoreCap": 44,
        "uiClass": "bad",
        "reason": "Authoritative signal is EXIT REVIEW; support labels are suppressed."
      },
      "composite": 44,
      "weakest": {
        "name": "Price trend",
        "score": 0,
        "status": "weak",
        "finding": "Day +5.63%, 5D -20.09%, 1M -32.47%, 3M -43.67%."
      },
      "strongest": {
        "name": "Portfolio concentration",
        "score": 98,
        "status": "supportive",
        "finding": "0.31% versus 5% speculative/levered budget."
      },
      "factors": [
        {
          "name": "Price trend",
          "score": 0,
          "status": "weak",
          "finding": "Day +5.63%, 5D -20.09%, 1M -32.47%, 3M -43.67%."
        },
        {
          "name": "Valuation",
          "score": 35,
          "status": "weak",
          "finding": "Forward PE and FCF yield missing."
        },
        {
          "name": "Portfolio concentration",
          "score": 98,
          "status": "supportive",
          "finding": "0.31% versus 5% speculative/levered budget."
        },
        {
          "name": "Earnings / event risk",
          "score": 45,
          "status": "mixed",
          "finding": "Earnings date N/A; timing unclear."
        },
        {
          "name": "Liquidity / flow",
          "score": 45,
          "status": "mixed",
          "finding": "Volume data missing."
        },
        {
          "name": "Macro sensitivity",
          "score": 34,
          "status": "weak",
          "finding": "Risk appetite: mixed / risk watch · Crypto liquidity beta: contracting · Credit conditions: benign / watch"
        },
        {
          "name": "Thesis confidence",
          "score": 68,
          "status": "mixed",
          "finding": "Thesis/rationale exists; check invalidation specificity."
        },
        {
          "name": "Data completeness",
          "score": 43,
          "status": "weak",
          "finding": "1/3 contract fields complete; price available."
        }
      ]
    },
    {
      "ticker": "SPY",
      "signal": "HOLD",
      "authority": {
        "state": "normal",
        "label": null,
        "scoreCap": 100,
        "uiClass": null,
        "reason": null
      },
      "composite": 46,
      "weakest": {
        "name": "Portfolio concentration",
        "score": 0,
        "status": "weak",
        "finding": "56.64% versus 15% single non-index budget."
      },
      "strongest": {
        "name": "Data completeness",
        "score": 90,
        "status": "supportive",
        "finding": "3/3 contract fields complete; price available."
      },
      "factors": [
        {
          "name": "Price trend",
          "score": 57,
          "status": "mixed",
          "finding": "Day -0.26%, 5D -1.93%, 1M -2.41%, 3M +12.12%."
        },
        {
          "name": "Valuation",
          "score": 66,
          "status": "mixed",
          "finding": "Forward PE 22.10; FCF yield 3.30%."
        },
        {
          "name": "Portfolio concentration",
          "score": 0,
          "status": "weak",
          "finding": "56.64% versus 15% single non-index budget."
        },
        {
          "name": "Earnings / event risk",
          "score": 45,
          "status": "mixed",
          "finding": "Earnings date N/A; timing unclear."
        },
        {
          "name": "Liquidity / flow",
          "score": 45,
          "status": "mixed",
          "finding": "Volume data missing."
        },
        {
          "name": "Macro sensitivity",
          "score": 4,
          "status": "weak",
          "finding": "Rates pressure: rising / restrictive · Risk appetite: mixed / risk watch · Credit conditions: benign / watch · Inflation expectation: contained watch"
        },
        {
          "name": "Thesis confidence",
          "score": 60,
          "status": "mixed",
          "finding": "Thesis/rationale exists; check invalidation specificity."
        },
        {
          "name": "Data completeness",
          "score": 90,
          "status": "supportive",
          "finding": "3/3 contract fields complete; price available."
        }
      ]
    },
    {
      "ticker": "MA",
      "signal": "HOLD",
      "authority": {
        "state": "normal",
        "label": null,
        "scoreCap": 100,
        "uiClass": null,
        "reason": null
      },
      "composite": 66,
      "weakest": {
        "name": "Macro sensitivity",
        "score": 41,
        "status": "weak",
        "finding": "Inflation expectation: contained watch"
      },
      "strongest": {
        "name": "Portfolio concentration",
        "score": 94,
        "status": "supportive",
        "finding": "3.59% versus 15% single non-index budget."
      },
      "factors": [
        {
          "name": "Price trend",
          "score": 53,
          "status": "mixed",
          "finding": "Day +2.25%, 5D +2.07%, 1M +0.99%, 3M +0.20%."
        },
        {
          "name": "Valuation",
          "score": 66,
          "status": "mixed",
          "finding": "Forward PE 28.90; FCF yield 2.60%."
        },
        {
          "name": "Portfolio concentration",
          "score": 94,
          "status": "supportive",
          "finding": "3.59% versus 15% single non-index budget."
        },
        {
          "name": "Earnings / event risk",
          "score": 75,
          "status": "supportive",
          "finding": "Next earnings in 24 trading days."
        },
        {
          "name": "Liquidity / flow",
          "score": 45,
          "status": "mixed",
          "finding": "Volume data missing."
        },
        {
          "name": "Macro sensitivity",
          "score": 41,
          "status": "weak",
          "finding": "Inflation expectation: contained watch"
        },
        {
          "name": "Thesis confidence",
          "score": 60,
          "status": "mixed",
          "finding": "Thesis/rationale exists; check invalidation specificity."
        },
        {
          "name": "Data completeness",
          "score": 90,
          "status": "supportive",
          "finding": "3/3 contract fields complete; price available."
        }
      ]
    },
    {
      "ticker": "BMNR",
      "signal": "INVESTIGATE",
      "authority": {
        "state": "investigate",
        "label": "Investigate",
        "scoreCap": 54,
        "uiClass": "warn",
        "reason": "Authoritative signal is INVESTIGATE; support labels are suppressed until verified."
      },
      "composite": 46,
      "weakest": {
        "name": "Price trend",
        "score": 0,
        "status": "weak",
        "finding": "Day +1.88%, 5D -15.92%, 1M -27.90%, 3M -34.76%."
      },
      "strongest": {
        "name": "Earnings / event risk",
        "score": 75,
        "status": "supportive",
        "finding": "Next earnings in 33 trading days."
      },
      "factors": [
        {
          "name": "Price trend",
          "score": 0,
          "status": "weak",
          "finding": "Day +1.88%, 5D -15.92%, 1M -27.90%, 3M -34.76%."
        },
        {
          "name": "Valuation",
          "score": 38,
          "status": "weak",
          "finding": "Forward PE missing; FCF yield -8.50%."
        },
        {
          "name": "Portfolio concentration",
          "score": 20,
          "status": "weak",
          "finding": "8.25% versus 5% speculative/levered budget."
        },
        {
          "name": "Earnings / event risk",
          "score": 75,
          "status": "supportive",
          "finding": "Next earnings in 33 trading days."
        },
        {
          "name": "Liquidity / flow",
          "score": 45,
          "status": "mixed",
          "finding": "Volume data missing."
        },
        {
          "name": "Macro sensitivity",
          "score": 55,
          "status": "mixed",
          "finding": "No explicit macro force mapped."
        },
        {
          "name": "Thesis confidence",
          "score": 68,
          "status": "mixed",
          "finding": "Thesis/rationale exists; check invalidation specificity."
        },
        {
          "name": "Data completeness",
          "score": 67,
          "status": "mixed",
          "finding": "2/3 contract fields complete; price available."
        }
      ]
    },
    {
      "ticker": "TSNF",
      "signal": "INVESTIGATE",
      "authority": {
        "state": "investigate",
        "label": "Investigate",
        "scoreCap": 54,
        "uiClass": "warn",
        "reason": "Authoritative signal is INVESTIGATE; support labels are suppressed until verified."
      },
      "composite": 54,
      "weakest": {
        "name": "Liquidity / flow",
        "score": 45,
        "status": "mixed",
        "finding": "Volume data missing."
      },
      "strongest": {
        "name": "Data completeness",
        "score": 90,
        "status": "supportive",
        "finding": "3/3 contract fields complete; price available."
      },
      "factors": [
        {
          "name": "Price trend",
          "score": 67,
          "status": "mixed",
          "finding": "Day +0.14%, 5D -4.49%, 1M -4.84%, 3M +29.78%."
        },
        {
          "name": "Valuation",
          "score": 66,
          "status": "mixed",
          "finding": "Forward PE 18.50; FCF yield 3.80%."
        },
        {
          "name": "Portfolio concentration",
          "score": 89,
          "status": "supportive",
          "finding": "2.26% versus 5% speculative/levered budget."
        },
        {
          "name": "Earnings / event risk",
          "score": 75,
          "status": "supportive",
          "finding": "Next earnings in 30 trading days."
        },
        {
          "name": "Liquidity / flow",
          "score": 45,
          "status": "mixed",
          "finding": "Volume data missing."
        },
        {
          "name": "Macro sensitivity",
          "score": 55,
          "status": "mixed",
          "finding": "No explicit macro force mapped."
        },
        {
          "name": "Thesis confidence",
          "score": 68,
          "status": "mixed",
          "finding": "Thesis/rationale exists; check invalidation specificity."
        },
        {
          "name": "Data completeness",
          "score": 90,
          "status": "supportive",
          "finding": "3/3 contract fields complete; price available."
        }
      ]
    },
    {
      "ticker": "NFLX",
      "signal": "HOLD / WATCH",
      "authority": {
        "state": "normal",
        "label": null,
        "scoreCap": 100,
        "uiClass": null,
        "reason": null
      },
      "composite": 59,
      "weakest": {
        "name": "Price trend",
        "score": 22,
        "status": "weak",
        "finding": "Day +4.10%, 5D -4.62%, 1M -15.51%, 3M -18.82%."
      },
      "strongest": {
        "name": "Portfolio concentration",
        "score": 95,
        "status": "supportive",
        "finding": "3.30% versus 15% single non-index budget."
      },
      "factors": [
        {
          "name": "Price trend",
          "score": 22,
          "status": "weak",
          "finding": "Day +4.10%, 5D -4.62%, 1M -15.51%, 3M -18.82%."
        },
        {
          "name": "Valuation",
          "score": 66,
          "status": "mixed",
          "finding": "Forward PE 24.20; FCF yield 3.60%."
        },
        {
          "name": "Portfolio concentration",
          "score": 95,
          "status": "supportive",
          "finding": "3.30% versus 15% single non-index budget."
        },
        {
          "name": "Earnings / event risk",
          "score": 55,
          "status": "mixed",
          "finding": "Next earnings in 15 trading days."
        },
        {
          "name": "Liquidity / flow",
          "score": 45,
          "status": "mixed",
          "finding": "Volume data missing."
        },
        {
          "name": "Macro sensitivity",
          "score": 29,
          "status": "weak",
          "finding": "Rates pressure: rising / restrictive · Inflation expectation: contained watch"
        },
        {
          "name": "Thesis confidence",
          "score": 68,
          "status": "mixed",
          "finding": "Thesis/rationale exists; check invalidation specificity."
        },
        {
          "name": "Data completeness",
          "score": 90,
          "status": "supportive",
          "finding": "3/3 contract fields complete; price available."
        }
      ]
    }
  ],
  "policy": "computedSignal is authoritative over score support labels; EXIT/TRIM/INVESTIGATE cannot appear as Strong support."
}